mimiqcircuits/__init__.py
mimiqcircuits/__version__.py
mimiqcircuits/bitstrings.py
mimiqcircuits/canvas.py
mimiqcircuits/circuit.py
mimiqcircuits/classical/classical_not.py
mimiqcircuits/complex.py
mimiqcircuits/gatedecl.py
mimiqcircuits/hamiltonian.py
mimiqcircuits/instruction.py
mimiqcircuits/lazy.py
mimiqcircuits/matrices.py
mimiqcircuits/operations/__init__.py
mimiqcircuits/operations/amplitude.py
mimiqcircuits/operations/annotations.py
mimiqcircuits/operations/barrier.py
mimiqcircuits/operations/block.py
mimiqcircuits/operations/control.py
mimiqcircuits/operations/decompositions/control.py
mimiqcircuits/operations/entanglement.py
mimiqcircuits/operations/expectationvalue.py
mimiqcircuits/operations/gates/__init__.py
mimiqcircuits/operations/gates/custom.py
mimiqcircuits/operations/gates/delay.py
mimiqcircuits/operations/gates/gate.py
mimiqcircuits/operations/gates/generalized/__init__.py
mimiqcircuits/operations/gates/generalized/diffusion.py
mimiqcircuits/operations/gates/generalized/paulistring.py
mimiqcircuits/operations/gates/generalized/phasegradient.py
mimiqcircuits/operations/gates/generalized/polynomialoracle.py
mimiqcircuits/operations/gates/generalized/qft.py
mimiqcircuits/operations/gates/generalized/rnz.py
mimiqcircuits/operations/gates/generalized/rpauli.py
mimiqcircuits/operations/gates/standard/__init__.py
mimiqcircuits/operations/gates/standard/chadamard.py
mimiqcircuits/operations/gates/standard/cnp.py
mimiqcircuits/operations/gates/standard/cnx.py
mimiqcircuits/operations/gates/standard/cpauli.py
mimiqcircuits/operations/gates/standard/cphase.py
mimiqcircuits/operations/gates/standard/crotations.py
mimiqcircuits/operations/gates/standard/cs.py
mimiqcircuits/operations/gates/standard/cswap.py
mimiqcircuits/operations/gates/standard/csx.py
mimiqcircuits/operations/gates/standard/cu.py
mimiqcircuits/operations/gates/standard/dcx.py
mimiqcircuits/operations/gates/standard/deprecated.py
mimiqcircuits/operations/gates/standard/ecr.py
mimiqcircuits-0.18.1.dist-info/LICENSE
mimiqcircuits-0.18.1.dist-info/METADATA
mimiqcircuits-0.18.1.dist-info/WHEEL
mimiqcircuits-0.18.1.dist-info/RECORD
