Metadata-Version: 2.3
Name: mimiqcircuits
Version: 0.18.1
Summary: User API for MIMIQ by QPerfect. Build quantum circuits, schedule remote simulations, and explore simulation results.
License: Apache-2.0
Author: Guido Masella
Author-email: guido.masella@qperfect.io
Requires-Python: >=3.9,<4
Classifier: License :: OSI Approved :: Apache Software License
Classifier: Programming Language :: Python :: 3
Classifier: Programming Language :: Python :: 3.9
Classifier: Programming Language :: Python :: 3.10
Classifier: Programming Language :: Python :: 3.11
Classifier: Programming Language :: Python :: 3.12
Classifier: Programming Language :: Python :: 3.13
Provides-Extra: visualization
Requires-Dist: bitarray (>=2.9,<3)
Requires-Dist: matplotlib (>=3.8,<4) ; extra == "visualization"
Requires-Dist: mimiqlink (>=0.8,<0.9)
Requires-Dist: numpy (>=1.26,<3.0)
Requires-Dist: protobuf (>=6.30,<7)
Requires-Dist: scipy (>=1.13,<2)
Requires-Dist: symengine (>=0.11,<1.0)
Requires-Dist: sympy (>=1.12,<2)
Project-URL: Documentation, https://docs.qperfect.io
Project-URL: Repository, https://github.com/qperfect-io/mimiqcircuits-python
